README.md
setup.py
mkdocs_auto_i18n/__init__.py
mkdocs_auto_i18n.egg-info/PKG-INFO
mkdocs_auto_i18n.egg-info/SOURCES.txt
mkdocs_auto_i18n.egg-info/dependency_links.txt
mkdocs_auto_i18n.egg-info/requires.txt
mkdocs_auto_i18n.egg-info/top_level.txt